image_analyst/tf/__init__.py
image_analyst/tf/models.py
image_analyst_tf-0.2.0.dist-info/LICENSE
image_analyst_tf-0.2.0.dist-info/METADATA
image_analyst_tf-0.2.0.dist-info/WHEEL
image_analyst_tf-0.2.0.dist-info/RECORD
