Metadata-Version: 2.1
Name: image-analyst-tf
Version: 0.2.0
Summary: ImageAnalyst TF is an extension to the ImageAnalyst library, providing additional models and functions using tensorflow.
Home-page: https://github.com/BergLucas/ImageAnalystTF
Keywords: image,analysis,tensorflow
Author: Lucas Berg
Author-email: 55436804+BergLucas@users.noreply.github.com
Requires-Python: >=3.9,<3.12
Classifier: Development Status :: 3 - Alpha
Classifier: License :: OSI Approved :: MIT License
Classifier: Programming Language :: Python :: 3
Classifier: Programming Language :: Python :: 3.9
Classifier: Programming Language :: Python :: 3.10
Classifier: Programming Language :: Python :: 3.11
Requires-Dist: image-analyst (>=0.2.0,<0.3.0)
Requires-Dist: numpy (>=1.24.3,<2.0.0)
Requires-Dist: tensorflow (>=2.10.0,<3.0.0)
Requires-Dist: tensorflow-io-gcs-filesystem (>=0.29,<0.30)
Project-URL: Repository, https://github.com/BergLucas/ImageAnalystTF
